schema_sync/__init__.py
schema_sync/cli.py
schema_sync/compare.py
schema_sync/infer.py
schema_sync/validate.py
csv_json_schema_sync-0.1.2.dist-info/METADATA
csv_json_schema_sync-0.1.2.dist-info/WHEEL
csv_json_schema_sync-0.1.2.dist-info/entry_points.txt
csv_json_schema_sync-0.1.2.dist-info/top_level.txt
csv_json_schema_sync-0.1.2.dist-info/RECORD
