Metadata-Version: 2.4
Name: csv-json-schema-sync
Version: 0.1.2
Summary: A tool for data engineers to manage continuously evolving CSV/JSON schemas.
Author-email: Azmat Siddique <azmat.siddique.98@gmail.com>
License: MIT
Project-URL: Repository, https://github.com/azmatsiddique/schema-sync-tool
Requires-Python: >=3.8
Requires-Dist: pandas
Requires-Dist: jsonschema
Requires-Dist: rich
Provides-Extra: dev
Requires-Dist: pytest; extra == "dev"
